pyrun_jupyter/__init__.py
pyrun_jupyter/__init__.pyi
pyrun_jupyter/contents.py
pyrun_jupyter/exceptions.py
pyrun_jupyter/kernel.py
pyrun_jupyter/result.py
pyrun_jupyter/result.pyi
pyrun_jupyter/runner.py
pyrun_jupyter/runner.pyi
pyrun_jupyter/websocket.py
pyrun_jupyter-0.4.0.dist-info/licenses/LICENSE
pyrun_jupyter-0.4.0.dist-info/METADATA
pyrun_jupyter-0.4.0.dist-info/WHEEL
pyrun_jupyter-0.4.0.dist-info/top_level.txt
pyrun_jupyter-0.4.0.dist-info/RECORD
