Metadata-Version: 2.4
Name: pyrun-jupyter
Version: 0.4.0
Summary: Execute Python .py files on remote Jupyter servers
Author: Blazej Domagala
License: MIT
Project-URL: Homepage, https://github.com/petitoff/pyrun-jupyter
Project-URL: Repository, https://github.com/petitoff/pyrun-jupyter
Project-URL: Issues, https://github.com/petitoff/pyrun-jupyter/issues
Keywords: jupyter,remote,execution,kernel,python
Classifier: Development Status :: 3 - Alpha
Classifier: Intended Audience :: Developers
Classifier: License :: OSI Approved :: MIT License
Classifier: Operating System :: OS Independent
Classifier: Programming Language :: Python :: 3
Classifier: Programming Language :: Python :: 3.8
Classifier: Programming Language :: Python :: 3.9
Classifier: Programming Language :: Python :: 3.10
Classifier: Programming Language :: Python :: 3.11
Classifier: Programming Language :: Python :: 3.12
Classifier: Topic :: Software Development :: Libraries :: Python Modules
Requires-Python: >=3.8
License-File: LICENSE
Requires-Dist: requests>=2.25.0
Requires-Dist: websocket-client>=1.0.0
Provides-Extra: dev
Requires-Dist: pytest>=7.0.0; extra == "dev"
Requires-Dist: pytest-cov>=4.0.0; extra == "dev"
Dynamic: license-file
